{"화폐": [
    "통화",
    "정금",
    "정화",
    "돈",
    "재폐",
    "동전",
    "금전"
],
"가상": [
    "허상",
    "상상",
    "가상계좌",
    "변질가상",
    "칭찬",
    "가공"
],
"주": [
    "주간",
    "하나님",
    "주권",
    "주체",
    "그루",
    "예수",
    "주식"
],
"시": [
    "도시",
    "시간",
    "때",
    "동시",
    "시각",
    "가집",
    "시집"
],
"대한민국": [
    "한",
    "남한",
    "한국",
    "상해임시정부",
    "임시정부" 
],
"출국": [
    "입국",
    "출국장",
    "귀국",
    "순방"
],
"정부": [
    "행정부",
    "정랑",
    "전사",
    "정인",
    "군계집",
    "샛서방"
],
"국회": [
    "입법부",
    "의회",
    "국무회의",
    "국민대표",
    "국회법"
],
"전": [
    "밭전",
    "모든",
    "전집",
    "과거",
    "이전"
],
"앞": [
    "앞쪽",
    "앞길",
    "앞면",
    "앞뒤",
    "미래"
],
"개인": [
    "개체주의",
    "타인",
    "일사인",
    "답인",
    "개인별",
    "일개인"

],
"집": [
    "집짓기",
    "집안",
    "집값",
    "가정",
    "우리집",
    "가족",
    "가옥"
],
"공유": [
    "국유",
    "공동",
    "생각",
    "공동소유"
],
"이상": [
    "비전",
    "이념",
    "별상",
    "괴상"
],
"문재인": [],
"오늘": [
    "요새",
    "요즘",
    "본일",
    "오날나라",
    "요즈음"
],
"마지막": [
    "궁극",
    "끝",
    "마지막",
    "막딸",
    "최종",
    "결국"
],
"사건": [
    "사안",
    "문제",
    "참사",
    "사변",
    "사태",
    "사고"
],
"느낌": [
    "감정",
    "감개",
    "감각",
    "감탄법"
],
"개": [
    "강아지",
    "견공",
    "진돗개"
],
"의원": [
    "귤정",
    "병의원",
    "의사",
    "의생"
],
"아이": [
    "소아",
    "새끼",
    "아이고",
    "아유",
    "아기"
],
"문제": [
    "말썽거리",
    "말썽",
    "글제",
    "문제아"
],
"줄": [
    "침고",
    "줄풀",
    "쇠줄",
    "끈",
    "노끈"
],
"끝": [
    "마지막",
    "봉첨",
    "가장자리",
    "종뇌",
    "결과"
],
"수사": [
    "수량대명사",
    "수대명사",
    "수사법",
    "사득",
    "수기",
    "수도사",
    "친서"
],
"정책": [
    "전략",
    "시책",
    "방침",
    "제도",
    "정치"
],
"만": [
],
"국민연금": [
],
"작품": [
    "걸작품",
    "물품",
    "예술",
    "예술품",
    "소작",
    "미술"
],
"시작": [
    "시작인",
    "개막",
    "처음"
],
"점": [
    "부점",
    "반점",
    "섬",
    "사주",
    "주막",
    "복서",
    "복술"
],
"여성": [
    "여성부",
    "여성",
    "여자",
    "여성용",
    "부녀자",
    "계집",
    "숙녀"
],
"보호법": [
    "노동보호법",
    "근로보호법"
],
"국가": [
    "방가",
    "정부",
    "애국가",
    "국기",
    "법치국",
    "나라"
],
"이번": [
    "금차",
    "요번",
    "금번"
],
"후": [
    "왕비",
    "후유",
    "나중",
    "뒤",
    "이후",
    "후비",
    "왕후"
],
"공무원": [
    "소방수",
    "공직자",
    "소방관",
    "공무원",
    "경찰관"
],
"의무": [
    "권리",
    "본분",
    "임무",
    "강제교육",
    "의무적",
    "의무감",
    "과업"
],
"편": [
    "한편",
    "방향",
    "내편",
    "절병",
    "수",
    "절편",
    "쪽"
],
"마음": [
    "감정",
    "가슴속",
    "정신",
    "내면세계",
    "생각",
    "가슴",
    "마음속"
],
"댓글": [
    "답글",
    "악플",
    "덧글",
    "선플"
],
"교육": [
    "성인교육",
    "교양",
    "교육부",
    "과정"
],
"운동": [
    "걷기",
    "스포츠",
    "경기",
    "활동",
    "축구",
    "농구"
],
"가능": [
    "가능성"
],
"파면": [
    "경질",
    "해고",
    "강등",
    "탄핵",
    "정직",
    "파직"
],
"곳": [
    "군데",
    "곧",
    "한곳",
    "자리",
    "위치",
    "곳간"
],
"규제": [
    "통제",
    "단속",
    "규정",
    "제한",
    "제재"
],
"부동산": [
    "부동산",
    "집",
    "땅",
    "토지",
    "아파트"
],
"데": [
],
"업무": [
    "상무",
    "용무",
    "볼일",
    "업무",
    "직무",
    "사무"
]}